{
  "date": "2026-05-19",
  "label": "19/05",
  "summary": {
    "fat": 554.26,
    "vnd": 41,
    "tkt": 13.52
  },
  "stores": [
    {
      "key": "albatroz",
      "name": "Albatroz",
      "fat": 274.65,
      "vnd": 19,
      "tkt": 14.46
    },
    {
      "key": "point",
      "name": "The Point Offices",
      "fat": 189.71,
      "vnd": 17,
      "tkt": 11.16
    },
    {
      "key": "tagus",
      "name": "Tagus II",
      "fat": 89.9,
      "vnd": 5,
      "tkt": 17.98
    }
  ],
  "generatedAt": "2026-05-19T22:42:58.324Z"
}