{
  "date": "2026-06-12",
  "label": "12/06",
  "summary": {
    "fat": 400.17,
    "vnd": 34,
    "tkt": 11.77
  },
  "stores": [
    {
      "key": "albatroz",
      "name": "Albatroz",
      "fat": 176.01,
      "vnd": 10,
      "tkt": 17.6
    },
    {
      "key": "point",
      "name": "The Point Offices",
      "fat": 112.26,
      "vnd": 15,
      "tkt": 7.48
    },
    {
      "key": "tagus",
      "name": "Tagus II",
      "fat": 111.9,
      "vnd": 9,
      "tkt": 12.43
    }
  ],
  "generatedAt": "2026-06-12T22:04:46.545Z"
}