{
  "date": "2026-04-02",
  "label": "02/04",
  "summary": {
    "fat": 333.82,
    "vnd": 27,
    "tkt": 12.36
  },
  "stores": [
    {
      "key": "albatroz",
      "name": "Albatroz",
      "fat": 140.85,
      "vnd": 13,
      "tkt": 10.83
    },
    {
      "key": "point",
      "name": "The Point Offices",
      "fat": 104.06,
      "vnd": 9,
      "tkt": 11.56
    },
    {
      "key": "tagus",
      "name": "Tagus II",
      "fat": 88.91,
      "vnd": 5,
      "tkt": 17.78
    }
  ],
  "generatedAt": "2026-04-02T21:03:03.453Z"
}