{
  "date": "2026-04-12",
  "label": "12/04",
  "summary": {
    "fat": 468.14,
    "vnd": 32,
    "tkt": 14.63
  },
  "stores": [
    {
      "key": "albatroz",
      "name": "Albatroz",
      "fat": 372.22,
      "vnd": 24,
      "tkt": 15.51
    },
    {
      "key": "tagus",
      "name": "Tagus II",
      "fat": 89.93,
      "vnd": 7,
      "tkt": 12.85
    },
    {
      "key": "point",
      "name": "The Point Offices",
      "fat": 5.99,
      "vnd": 1,
      "tkt": 5.99
    }
  ],
  "generatedAt": "2026-04-12T22:31:10.618Z"
}