{
  "date": "2026-03-31",
  "label": "31/03",
  "summary": {
    "fat": 320.29,
    "vnd": 24,
    "tkt": 13.35
  },
  "stores": [
    {
      "key": "albatroz",
      "name": "Albatroz",
      "fat": 237.21,
      "vnd": 18,
      "tkt": 13.18
    },
    {
      "key": "point",
      "name": "The Point Offices",
      "fat": 45.11,
      "vnd": 4,
      "tkt": 11.28
    },
    {
      "key": "tagus",
      "name": "Tagus II",
      "fat": 37.97,
      "vnd": 2,
      "tkt": 18.99
    }
  ],
  "generatedAt": "2026-03-31T22:54:28.615Z"
}